putio_downloader/__init__.py
putio_downloader/cli.py
putio_downloader/putio_aria2c_downloader.py
tests/__init__.py
tests/test_cli.py
tests/test_config.py
tests/test_crc.py
putio_downloader-3.1.4.dist-info/LICENSE
putio_downloader-3.1.4.dist-info/METADATA
putio_downloader-3.1.4.dist-info/WHEEL
putio_downloader-3.1.4.dist-info/entry_points.txt
putio_downloader-3.1.4.dist-info/top_level.txt
putio_downloader-3.1.4.dist-info/RECORD
